amharic_text_processor/__init__.py
amharic_text_processor/base.py
amharic_text_processor/pipeline.py
amharic_text_processor/assets/abbreviations.py
amharic_text_processor/assets/romanization.py
amharic_text_processor/processors/__init__.py
amharic_text_processor/processors/abbreviations.py
amharic_text_processor/processors/deduplication.py
amharic_text_processor/processors/filters.py
amharic_text_processor/processors/html.py
amharic_text_processor/processors/normalize.py
amharic_text_processor/processors/numbers.py
amharic_text_processor/processors/phonetic.py
amharic_text_processor/processors/tokenize.py
amharic_text_processor/processors/transliterate.py
amharic_text_processor/processors/whitespace.py
amharic_text_processor-0.1.3.dist-info/METADATA
amharic_text_processor-0.1.3.dist-info/WHEEL
amharic_text_processor-0.1.3.dist-info/top_level.txt
amharic_text_processor-0.1.3.dist-info/RECORD
