Metadata-Version: 2.4
Name: amharic-text-processor
Version: 0.1.3
Summary: A modular toolkit for cleaning and normalizing Amharic text.
Author-email: Ethiopic AI <contact@ethiopic.ai>
License: MIT
Project-URL: Homepage, https://github.com/isrish/Amharic-Text-Processor
Project-URL: Source, https://github.com/isrish/Amharic-Text-Processor
Project-URL: Tracker, https://github.com/isrish/Amharic-Text-Processor/issues
Keywords: amharic,text-processing,Linguistic,nlp,ethiopic,normalization
Classifier: Programming Language :: Python :: 3
Classifier: Programming Language :: Python :: 3.8
Classifier: Programming Language :: Python :: 3.9
Classifier: Programming Language :: Python :: 3.10
Classifier: Programming Language :: Python :: 3.11
Classifier: Programming Language :: Python :: 3.12
Classifier: Programming Language :: Python :: Implementation :: PyPy
Classifier: License :: OSI Approved :: MIT License
Classifier: Operating System :: OS Independent
Classifier: Intended Audience :: Developers
Classifier: Topic :: Text Processing :: Linguistic
Requires-Python: >=3.8
Requires-Dist: beautifulsoup4>=4.12
Requires-Dist: rapidfuzz>=3.0
